rad_measure/__init__.py
rad_measure/utils.py
rad_measure/vqa_utils.py
rad_measure-0.0.1.dist-info/LICENSE
rad_measure-0.0.1.dist-info/METADATA
rad_measure-0.0.1.dist-info/WHEEL
rad_measure-0.0.1.dist-info/top_level.txt
rad_measure-0.0.1.dist-info/RECORD
