Metadata-Version: 2.1
Name: rad-measure
Version: 0.0.1
Summary: Are VQA systems RAD? Measuring robustness to augmented data with focused interventions
Home-page: https://github.com/danrosenberg/rad-measure
Author: Daniel Rosenberg
Author-email: daniel.rnberg@gmail.com
License: UNKNOWN
Project-URL: Bug Tracker, https://github.com/danrosenberg/rad-measure/issues
Platform: UNKNOWN
Classifier: Programming Language :: Python :: 3
Classifier: License :: OSI Approved :: MIT License
Classifier: Operating System :: OS Independent
Requires-Python: >=3.6
License-File: LICENSE
